pyams_zmq/__init__.py
pyams_zmq/handler.py
pyams_zmq/include.py
pyams_zmq/interfaces.py
pyams_zmq/process.py
pyams_zmq/socket.py
pyams_zmq/doctests/README.rst
pyams_zmq/locales/pyams_zmq.pot
pyams_zmq/locales/fr/LC_MESSAGES/pyams_zmq.po
pyams_zmq/tests/__init__.py
pyams_zmq/tests/test_utilsdocs.py
pyams_zmq/tests/test_utilsdocstrings.py
pyams_zmq-2.0.0.dist-info/LICENSE
pyams_zmq-2.0.0.dist-info/METADATA
pyams_zmq-2.0.0.dist-info/WHEEL
pyams_zmq-2.0.0.dist-info/namespace_packages.txt
pyams_zmq-2.0.0.dist-info/top_level.txt
pyams_zmq-2.0.0.dist-info/RECORD
