Metadata-Version: 2.1
Name: pyams-zmq
Version: 2.0.0
Summary: PyAMS ZeroMQ helper package
Home-page: https://pyams.readthedocs.io
Author: Thierry Florac
Author-email: tflorac@ulthar.net
License: ZPL
Keywords: Pyramid PyAMS ZeroMQ
Classifier: License :: OSI Approved :: Zope Public License
Classifier: Development Status :: 4 - Beta
Classifier: Programming Language :: Python
Classifier: Framework :: Pyramid
Classifier: Topic :: Software Development :: Libraries :: Python Modules
License-File: LICENSE
Requires-Dist: setuptools
Requires-Dist: pyams-utils
Requires-Dist: pyramid >=2.0.0
Requires-Dist: pyzmq
Requires-Dist: tornado
Requires-Dist: zope.interface
Provides-Extra: test
Requires-Dist: pyramid-zcml ; extra == 'test'
Requires-Dist: zope.exceptions ; extra == 'test'
